Formule_Tariq/__init__.py
Formule_Tariq/tariq_formule.py
formule_tk_Tariq-0.0.1.dist-info/LICENSE.txt
formule_tk_Tariq-0.0.1.dist-info/METADATA
formule_tk_Tariq-0.0.1.dist-info/WHEEL
formule_tk_Tariq-0.0.1.dist-info/top_level.txt
formule_tk_Tariq-0.0.1.dist-info/RECORD
