Metadata-Version: 2.1
Name: formule-tk-Tariq
Version: 0.0.1
Summary: A tkinter application 
Author-email: Tariq Azdoud <tariqazdoud00@gmail.com>
Classifier: Programming Language :: Python :: 3
Classifier: License :: OSI Approved :: MIT License
Classifier: Operating System :: OS Independent
Requires-Python: >=3.7
License-File: LICENSE.txt
